chatman_controller/__init__.py
chatman_controller/chatman_cli.py
chatman_controller/chatman_controller.py
chatman_controller/chatman_gui.py
chatman_controller-0.1.2.dist-info/licenses/LICENSE
chatman_controller-0.1.2.dist-info/METADATA
chatman_controller-0.1.2.dist-info/WHEEL
chatman_controller-0.1.2.dist-info/entry_points.txt
chatman_controller-0.1.2.dist-info/top_level.txt
chatman_controller-0.1.2.dist-info/RECORD
