Metadata-Version: 2.4
Name: chatman_controller
Version: 0.1.2
Summary: A reverse-engineered controller for the Chatman toy
Author-email: mohelm97 <mohelm97@gmail.com>
License-Expression: MIT
Project-URL: Homepage, https://github.com/mohelm97/chatman-controller
Project-URL: Repository, https://github.com/mohelm97/chatman-controller
License-File: LICENSE
Requires-Dist: hidapi
Dynamic: license-file
